browbeat/__init__.py
browbeat/config.py
browbeat/elastic.py
browbeat/grafana.py
browbeat/metadata.py
browbeat/path.py
browbeat/perfkit.py
browbeat/rally.py
browbeat/shaker.py
browbeat/tools.py
browbeat/workloadbase.py
browbeat/yoda.py
browbeat/schema/browbeat.yml
browbeat/schema/perfkit.yml
browbeat/schema/rally.yml
browbeat/schema/shaker.yml
browbeat/schema/yoda.yml
browbeat-0.0.1.dev1290.data/data/playbooks/baremetal-virt-undercloud-int-browbeat.yml
browbeat-0.0.1.dev1290.data/data/playbooks/baremetal-virt-undercloud-tripleo-browbeat.yml
browbeat-0.0.1.dev1290.data/data/playbooks/baremetal-virt-undercloud-yoda-browbeat.yml
browbeat-0.0.1.dev1290.data/data/playbooks/browbeat-minimal.yml
browbeat-0.0.1.dev1290.data/data/playbooks/configure-browbeat.yml
browbeat-0.0.1.dev1290.data/data/playbooks/disable-ssh-dns.yml
browbeat-0.0.1.dev1290.data/data/playbooks/gather-metadata.yml
browbeat-0.0.1.dev1290.data/data/playbooks/install-browbeat.yml
browbeat-0.0.1.dev1290.data/data/playbooks/overcloud-metrics.yml
browbeat-0.0.1.dev1290.data/data/playbooks/quickstart-browbeat.yml
browbeat-0.0.1.dev1290.data/data/playbooks/undercloud-metrics.yml
browbeat-0.0.1.dev1290.data/data/playbooks/roles/browbeat-classify/files/uuid_extract.sh
browbeat-0.0.1.dev1290.data/data/playbooks/roles/browbeat-classify/tasks/main.yml
browbeat-0.0.1.dev1290.data/data/playbooks/roles/browbeat-run/tasks/main.yml
browbeat-0.0.1.dev1290.data/data/playbooks/roles/bug-check/tasks/main.yml
browbeat-0.0.1.dev1290.data/data/playbooks/roles/ci-network/defaults/main.yml
browbeat-0.0.1.dev1290.data/data/playbooks/roles/ci-network/tasks/main.yml
browbeat-0.0.1.dev1290.data/data/playbooks/roles/collectd/tasks/main.yml
browbeat-0.0.1.dev1290.data/data/playbooks/roles/collectd/vars/main.yml
browbeat-0.0.1.dev1290.data/data/playbooks/roles/collectd-undercloud/tasks/main.yml
browbeat-0.0.1.dev1290.data/data/playbooks/roles/collectd-undercloud/templates/hosts.j2
browbeat-0.0.1.dev1290.dist-info/LICENSE
browbeat-0.0.1.dev1290.dist-info/METADATA
browbeat-0.0.1.dev1290.dist-info/WHEEL
browbeat-0.0.1.dev1290.dist-info/pbr.json
browbeat-0.0.1.dev1290.dist-info/top_level.txt
browbeat-0.0.1.dev1290.dist-info/RECORD
