Metadata-Version: 2.1
Name: browbeat
Version: 0.0.1.dev1290
Summary: OpenStack Performance Tooling
Home-page: http://www.browbeatproject.org/
Author: OpenStack
Author-email: openstack-dev@lists.openstack.org
License: UNKNOWN
Platform: UNKNOWN
Classifier: Environment :: OpenStack
Classifier: Intended Audience :: Information Technology
Classifier: Intended Audience :: System Administrators
Classifier: License :: OSI Approved :: Apache Software License
Classifier: Operating System :: POSIX :: Linux
Classifier: Programming Language :: Python
Classifier: Programming Language :: Python :: 2
Classifier: Programming Language :: Python :: 2.7
Classifier: Programming Language :: Python :: 3
Classifier: Programming Language :: Python :: 3.5
Requires-Dist: ansible (==2.4.1)
Requires-Dist: numpy
Requires-Dist: elasticsearch
Requires-Dist: grafyaml (==0.0.7)
Requires-Dist: openstacksdk
Requires-Dist: python-dateutil (==2.4.2)
Requires-Dist: python-openstackclient (==3.11.0)
Requires-Dist: pykwalify (==1.6.0)
